Metadata-Version: 2.1
Name: SwanGPT
Version: 0.0.0
Summary: swan-gpt
